{
    "laboratorios": [
        {"Fecha": 1234,
            "Creatinina": 4321,
            "BUN": 777,
            "Ca": 1234,
            "Calcio Total": 1234,
            "Fosforo": 1234,
            "LDH": 1234,
            "Magnesio": 1234,
            "Na+": 1234,
            "K+": 1234,
            "Cl-": 1234,
            "Bilirrubina Total": 1234,
            "Bilirrubina Directa": 1234,
            "ASAT": 1234,
            "ALAT": 1234,
            "GamaGT": 1234,
            "Fosfatasas Alcalinas": 1234,
            "PCR": 1234,
            "Lactato": 1234,
            "Albumina": 1234,
            "Proteinas Totales": 1234,
            "Glucosa": 1234,
            "Trigliceridos": 1234,
            "CK Total": 1234,
            "CK-MB": 1234,
            "TroponinaI": 1234,
            "proBNP": 1234,
            "Hb": 1234,
            "VCM": 1234,
            "HCM": 1234,
            "CHCM": 1234,
            "Plaquetas": 1234,
            "Leucocitos": 1234,
            "Segmentados": 1234,
            "Eosinofilos": 1234,
            "Linfocitos": 1234,
            "Monocitos": 1234,
            "Basofilos": 1234,
            "VHS": 1234,
            "INR": 1234,
            "TP": 1234,
            "TTPK": 1234,
            "pH": 1234,
            "pO2": 1234,
            "pCO2": 1234,
            "HCO3": 1234,
            "BE": 1234,
            "sO2": 1234},
        {"Fecha": 22222222,
            "Creatinina": 22222222,
            "BUN": 22222222,
            "Ca": 22222222,
            "Calcio Total": 22222222,
            "Fosforo": 22222222,
            "LDH": 22222222,
            "Magnesio": 22222222,
            "Na+": 22222222,
            "K+": 22222222,
            "Cl-": 22222222,
            "Bilirrubina Total": 22222222,
            "Bilirrubina Directa": 22222222,
            "ASAT": 22222222,
            "ALAT": 22222222,
            "GamaGT": 22222222,
            "Fosfatasas Alcalinas": 22222222,
            "PCR": 22222222,
            "Lactato": 22222222,
            "Albumina": 22222222,
            "Proteinas Totales": 22222222,
            "Glucosa": 22222222,
            "Trigliceridos": 22222222,
            "CK Total": 22222222,
            "CK-MB": 22222222,
            "TroponinaI": 22222222,
            "proBNP": 22222222,
            "Hb": 22222222,
            "VCM": 22222222,
            "HCM": 22222222,
            "CHCM": 22222222,
            "Plaquetas": 22222222,
            "Leucocitos": 22222222,
            "Segmentados": 22222222,
            "Eosinofilos": 22222222,
            "Linfocitos": 22222222,
            "Monocitos": 22222222,
            "Basofilos": 22222222,
            "VHS": 22222222,
            "INR": 22222222,
            "TP": 22222222,
            "TTPK": 22222222,
            "pH": 22222222,
            "pO2": 22222222,
            "pCO2": 22222222,
            "HCO3": 22222222,
            "BE": 22222222,
            "sO2": 22222222},
        {"Fecha": 1234,
            "Creatinina": 4321,
            "BUN": 777,
            "Ca": 1234,
            "Calcio Total": 1234,
            "Fosforo": 1234,
            "LDH": 1234,
            "Magnesio": 1234,
            "Na+": 1234,
            "K+": 1234,
            "Cl-": 1234,
            "Bilirrubina Total": 1234,
            "Bilirrubina Directa": 1234,
            "ASAT": 1234,
            "ALAT": 1234,
            "GamaGT": 1234,
            "Fosfatasas Alcalinas": 1234,
            "PCR": 1234,
            "Lactato": 1234,
            "Albumina": 1234,
            "Proteinas Totales": 1234,
            "Glucosa": 1234,
            "Trigliceridos": 1234,
            "CK Total": 1234,
            "CK-MB": 1234,
            "TroponinaI": 1234,
            "proBNP": 1234,
            "Hb": 1234,
            "VCM": 1234,
            "HCM": 1234,
            "CHCM": 1234,
            "Plaquetas": 1234,
            "Leucocitos": 1234,
            "Segmentados": 1234,
            "Eosinofilos": 1234,
            "Linfocitos": 1234,
            "Monocitos": 1234,
            "Basofilos": 1234,
            "VHS": 1234,
            "INR": 1234,
            "TP": 1234,
            "TTPK": 1234,
            "pH": 1234,
            "pO2": 1234,
            "pCO2": 1234,
            "HCO3": 1234,
            "BE": 1234,
            "sO2": 1234},
        {"Fecha": 22222222,
            "Creatinina": 22222222,
            "BUN": 22222222,
            "Ca": 22222222,
            "Calcio Total": 22222222,
            "Fosforo": 22222222,
            "LDH": 22222222,
            "Magnesio": 22222222,
            "Na+": 22222222,
            "K+": 22222222,
            "Cl-": 22222222,
            "Bilirrubina Total": 22222222,
            "Bilirrubina Directa": 22222222,
            "ASAT": 22222222,
            "ALAT": 22222222,
            "GamaGT": 22222222,
            "Fosfatasas Alcalinas": 22222222,
            "PCR": 22222222,
            "Lactato": 22222222,
            "Albumina": 22222222,
            "Proteinas Totales": 22222222,
            "Glucosa": 22222222,
            "Trigliceridos": 22222222,
            "CK Total": 22222222,
            "CK-MB": 22222222,
            "TroponinaI": 22222222,
            "proBNP": 22222222,
            "Hb": 22222222,
            "VCM": 22222222,
            "HCM": 22222222,
            "CHCM": 22222222,
            "Plaquetas": 22222222,
            "Leucocitos": 22222222,
            "Segmentados": 22222222,
            "Eosinofilos": 22222222,
            "Linfocitos": 22222222,
            "Monocitos": 22222222,
            "Basofilos": 22222222,
            "VHS": 22222222,
            "INR": 22222222,
            "TP": 22222222,
            "TTPK": 22222222,
            "pH": 22222222,
            "pO2": 22222222,
            "pCO2": 22222222,
            "HCO3": 22222222,
            "BE": 22222222,
            "sO2": 22222222},
        {"Fecha": 1234,
            "Creatinina": 4321,
            "BUN": 777,
            "Ca": 1234,
            "Calcio Total": 1234,
            "Fosforo": 1234,
            "LDH": 1234,
            "Magnesio": 1234,
            "Na+": 1234,
            "K+": 1234,
            "Cl-": 1234,
            "Bilirrubina Total": 1234,
            "Bilirrubina Directa": 1234,
            "ASAT": 1234,
            "ALAT": 1234,
            "GamaGT": 1234,
            "Fosfatasas Alcalinas": 1234,
            "PCR": 1234,
            "Lactato": 1234,
            "Albumina": 1234,
            "Proteinas Totales": 1234,
            "Glucosa": 1234,
            "Trigliceridos": 1234,
            "CK Total": 1234,
            "CK-MB": 1234,
            "TroponinaI": 1234,
            "proBNP": 1234,
            "Hb": 1234,
            "VCM": 1234,
            "HCM": 1234,
            "CHCM": 1234,
            "Plaquetas": 1234,
            "Leucocitos": 1234,
            "Segmentados": 1234,
            "Eosinofilos": 1234,
            "Linfocitos": 1234,
            "Monocitos": 1234,
            "Basofilos": 1234,
            "VHS": 1234,
            "INR": 1234,
            "TP": 1234,
            "TTPK": 1234,
            "pH": 1234,
            "pO2": 1234,
            "pCO2": 1234,
            "HCO3": 1234,
            "BE": 1234,
            "sO2": 1234},
        {"Fecha": 22222222,
            "Creatinina": 22222222,
            "BUN": 22222222,
            "Ca": 22222222,
            "Calcio Total": 22222222,
            "Fosforo": 22222222,
            "LDH": 22222222,
            "Magnesio": 22222222,
            "Na+": 22222222,
            "K+": 22222222,
            "Cl-": 22222222,
            "Bilirrubina Total": 22222222,
            "Bilirrubina Directa": 22222222,
            "ASAT": 22222222,
            "ALAT": 22222222,
            "GamaGT": 22222222,
            "Fosfatasas Alcalinas": 22222222,
            "PCR": 22222222,
            "Lactato": 22222222,
            "Albumina": 22222222,
            "Proteinas Totales": 22222222,
            "Glucosa": 22222222,
            "Trigliceridos": 22222222,
            "CK Total": 22222222,
            "CK-MB": 22222222,
            "TroponinaI": 22222222,
            "proBNP": 22222222,
            "Hb": 22222222,
            "VCM": 22222222,
            "HCM": 22222222,
            "CHCM": 22222222,
            "Plaquetas": 22222222,
            "Leucocitos": 22222222,
            "Segmentados": 22222222,
            "Eosinofilos": 22222222,
            "Linfocitos": 22222222,
            "Monocitos": 22222222,
            "Basofilos": 22222222,
            "VHS": 22222222,
            "INR": 22222222,
            "TP": 22222222,
            "TTPK": 22222222,
            "pH": 22222222,
            "pO2": 22222222,
            "pCO2": 22222222,
            "HCO3": 22222222,
            "BE": 22222222,
            "sO2": 22222222},
        {"Fecha": 1234,
            "Creatinina": 4321,
            "BUN": 777,
            "Ca": 1234,
            "Calcio Total": 1234,
            "Fosforo": 1234,
            "LDH": 1234,
            "Magnesio": 1234,
            "Na+": 1234,
            "K+": 1234,
            "Cl-": 1234,
            "Bilirrubina Total": 1234,
            "Bilirrubina Directa": 1234,
            "ASAT": 1234,
            "ALAT": 1234,
            "GamaGT": 1234,
            "Fosfatasas Alcalinas": 1234,
            "PCR": 1234,
            "Lactato": 1234,
            "Albumina": 1234,
            "Proteinas Totales": 1234,
            "Glucosa": 1234,
            "Trigliceridos": 1234,
            "CK Total": 1234,
            "CK-MB": 1234,
            "TroponinaI": 1234,
            "proBNP": 1234,
            "Hb": 1234,
            "VCM": 1234,
            "HCM": 1234,
            "CHCM": 1234,
            "Plaquetas": 1234,
            "Leucocitos": 1234,
            "Segmentados": 1234,
            "Eosinofilos": 1234,
            "Linfocitos": 1234,
            "Monocitos": 1234,
            "Basofilos": 1234,
            "VHS": 1234,
            "INR": 1234,
            "TP": 1234,
            "TTPK": 1234,
            "pH": 1234,
            "pO2": 1234,
            "pCO2": 1234,
            "HCO3": 1234,
            "BE": 1234,
            "sO2": 1234},
        {"Fecha": 22222222,
            "Creatinina": 22222222,
            "BUN": 22222222,
            "Ca": 22222222,
            "Calcio Total": 22222222,
            "Fosforo": 22222222,
            "LDH": 22222222,
            "Magnesio": 22222222,
            "Na+": 22222222,
            "K+": 22222222,
            "Cl-": 22222222,
            "Bilirrubina Total": 22222222,
            "Bilirrubina Directa": 22222222,
            "ASAT": 22222222,
            "ALAT": 22222222,
            "GamaGT": 22222222,
            "Fosfatasas Alcalinas": 22222222,
            "PCR": 22222222,
            "Lactato": 22222222,
            "Albumina": 22222222,
            "Proteinas Totales": 22222222,
            "Glucosa": 22222222,
            "Trigliceridos": 22222222,
            "CK Total": 22222222,
            "CK-MB": 22222222,
            "TroponinaI": 22222222,
            "proBNP": 22222222,
            "Hb": 22222222,
            "VCM": 22222222,
            "HCM": 22222222,
            "CHCM": 22222222,
            "Plaquetas": 22222222,
            "Leucocitos": 22222222,
            "Segmentados": 22222222,
            "Eosinofilos": 22222222,
            "Linfocitos": 22222222,
            "Monocitos": 22222222,
            "Basofilos": 22222222,
            "VHS": 22222222,
            "INR": 22222222,
            "TP": 22222222,
            "TTPK": 22222222,
            "pH": 22222222,
            "pO2": 22222222,
            "pCO2": 22222222,
            "HCO3": 22222222,
            "BE": 22222222,
            "sO2": 22222222},
        {"Fecha": 1234,
            "Creatinina": 4321,
            "BUN": 777,
            "Ca": 1234,
            "Calcio Total": 1234,
            "Fosforo": 1234,
            "LDH": 1234,
            "Magnesio": 1234,
            "Na+": 1234,
            "K+": 1234,
            "Cl-": 1234,
            "Bilirrubina Total": 1234,
            "Bilirrubina Directa": 1234,
            "ASAT": 1234,
            "ALAT": 1234,
            "GamaGT": 1234,
            "Fosfatasas Alcalinas": 1234,
            "PCR": 1234,
            "Lactato": 1234,
            "Albumina": 1234,
            "Proteinas Totales": 1234,
            "Glucosa": 1234,
            "Trigliceridos": 1234,
            "CK Total": 1234,
            "CK-MB": 1234,
            "TroponinaI": 1234,
            "proBNP": 1234,
            "Hb": 1234,
            "VCM": 1234,
            "HCM": 1234,
            "CHCM": 1234,
            "Plaquetas": 1234,
            "Leucocitos": 1234,
            "Segmentados": 1234,
            "Eosinofilos": 1234,
            "Linfocitos": 1234,
            "Monocitos": 1234,
            "Basofilos": 1234,
            "VHS": 1234,
            "INR": 1234,
            "TP": 1234,
            "TTPK": 1234,
            "pH": 1234,
            "pO2": 1234,
            "pCO2": 1234,
            "HCO3": 1234,
            "BE": 1234,
            "sO2": 1234},
        {"Fecha": 22222222,
            "Creatinina": 22222222,
            "BUN": 22222222,
            "Ca": 22222222,
            "Calcio Total": 22222222,
            "Fosforo": 22222222,
            "LDH": 22222222,
            "Magnesio": 22222222,
            "Na+": 22222222,
            "K+": 22222222,
            "Cl-": 22222222,
            "Bilirrubina Total": 22222222,
            "Bilirrubina Directa": 22222222,
            "ASAT": 22222222,
            "ALAT": 22222222,
            "GamaGT": 22222222,
            "Fosfatasas Alcalinas": 22222222,
            "PCR": 22222222,
            "Lactato": 22222222,
            "Albumina": 22222222,
            "Proteinas Totales": 22222222,
            "Glucosa": 22222222,
            "Trigliceridos": 22222222,
            "CK Total": 22222222,
            "CK-MB": 22222222,
            "TroponinaI": 22222222,
            "proBNP": 22222222,
            "Hb": 22222222,
            "VCM": 22222222,
            "HCM": 22222222,
            "CHCM": 22222222,
            "Plaquetas": 22222222,
            "Leucocitos": 22222222,
            "Segmentados": 22222222,
            "Eosinofilos": 22222222,
            "Linfocitos": 22222222,
            "Monocitos": 22222222,
            "Basofilos": 22222222,
            "VHS": 22222222,
            "INR": 22222222,
            "TP": 22222222,
            "TTPK": 22222222,
            "pH": 22222222,
            "pO2": 22222222,
            "pCO2": 22222222,
            "HCO3": 22222222,
            "BE": 22222222,
            "sO2": 22222222},
        {"Fecha": 1234,
            "Creatinina": 4321,
            "BUN": 777,
            "Ca": 1234,
            "Calcio Total": 1234,
            "Fosforo": 1234,
            "LDH": 1234,
            "Magnesio": 1234,
            "Na+": 1234,
            "K+": 1234,
            "Cl-": 1234,
            "Bilirrubina Total": 1234,
            "Bilirrubina Directa": 1234,
            "ASAT": 1234,
            "ALAT": 1234,
            "GamaGT": 1234,
            "Fosfatasas Alcalinas": 1234,
            "PCR": 1234,
            "Lactato": 1234,
            "Albumina": 1234,
            "Proteinas Totales": 1234,
            "Glucosa": 1234,
            "Trigliceridos": 1234,
            "CK Total": 1234,
            "CK-MB": 1234,
            "TroponinaI": 1234,
            "proBNP": 1234,
            "Hb": 1234,
            "VCM": 1234,
            "HCM": 1234,
            "CHCM": 1234,
            "Plaquetas": 1234,
            "Leucocitos": 1234,
            "Segmentados": 1234,
            "Eosinofilos": 1234,
            "Linfocitos": 1234,
            "Monocitos": 1234,
            "Basofilos": 1234,
            "VHS": 1234,
            "INR": 1234,
            "TP": 1234,
            "TTPK": 1234,
            "pH": 1234,
            "pO2": 1234,
            "pCO2": 1234,
            "HCO3": 1234,
            "BE": 1234,
            "sO2": 1234},
        {"Fecha": 22222222,
            "Creatinina": 22222222,
            "BUN": 22222222,
            "Ca": 22222222,
            "Calcio Total": 22222222,
            "Fosforo": 22222222,
            "LDH": 22222222,
            "Magnesio": 22222222,
            "Na+": 22222222,
            "K+": 22222222,
            "Cl-": 22222222,
            "Bilirrubina Total": 22222222,
            "Bilirrubina Directa": 22222222,
            "ASAT": 22222222,
            "ALAT": 22222222,
            "GamaGT": 22222222,
            "Fosfatasas Alcalinas": 22222222,
            "PCR": 22222222,
            "Lactato": 22222222,
            "Albumina": 22222222,
            "Proteinas Totales": 22222222,
            "Glucosa": 22222222,
            "Trigliceridos": 22222222,
            "CK Total": 22222222,
            "CK-MB": 22222222,
            "TroponinaI": 22222222,
            "proBNP": 22222222,
            "Hb": 22222222,
            "VCM": 22222222,
            "HCM": 22222222,
            "CHCM": 22222222,
            "Plaquetas": 22222222,
            "Leucocitos": 22222222,
            "Segmentados": 22222222,
            "Eosinofilos": 22222222,
            "Linfocitos": 22222222,
            "Monocitos": 22222222,
            "Basofilos": 22222222,
            "VHS": 22222222,
            "INR": 22222222,
            "TP": 22222222,
            "TTPK": 22222222,
            "pH": 22222222,
            "pO2": 22222222,
            "pCO2": 22222222,
            "HCO3": 22222222,
            "BE": 22222222,
            "sO2": 22222222},
        {"Fecha": 1234,
            "Creatinina": 4321,
            "BUN": 777,
            "Ca": 1234,
            "Calcio Total": 1234,
            "Fosforo": 1234,
            "LDH": 1234,
            "Magnesio": 1234,
            "Na+": 1234,
            "K+": 1234,
            "Cl-": 1234,
            "Bilirrubina Total": 1234,
            "Bilirrubina Directa": 1234,
            "ASAT": 1234,
            "ALAT": 1234,
            "GamaGT": 1234,
            "Fosfatasas Alcalinas": 1234,
            "PCR": 1234,
            "Lactato": 1234,
            "Albumina": 1234,
            "Proteinas Totales": 1234,
            "Glucosa": 1234,
            "Trigliceridos": 1234,
            "CK Total": 1234,
            "CK-MB": 1234,
            "TroponinaI": 1234,
            "proBNP": 1234,
            "Hb": 1234,
            "VCM": 1234,
            "HCM": 1234,
            "CHCM": 1234,
            "Plaquetas": 1234,
            "Leucocitos": 1234,
            "Segmentados": 1234,
            "Eosinofilos": 1234,
            "Linfocitos": 1234,
            "Monocitos": 1234,
            "Basofilos": 1234,
            "VHS": 1234,
            "INR": 1234,
            "TP": 1234,
            "TTPK": 1234,
            "pH": 1234,
            "pO2": 1234,
            "pCO2": 1234,
            "HCO3": 1234,
            "BE": 1234,
            "sO2": 1234},
        {"Fecha": 22222222,
            "Creatinina": 22222222,
            "BUN": 22222222,
            "Ca": 22222222,
            "Calcio Total": 22222222,
            "Fosforo": 22222222,
            "LDH": 22222222,
            "Magnesio": 22222222,
            "Na+": 22222222,
            "K+": 22222222,
            "Cl-": 22222222,
            "Bilirrubina Total": 22222222,
            "Bilirrubina Directa": 22222222,
            "ASAT": 22222222,
            "ALAT": 22222222,
            "GamaGT": 22222222,
            "Fosfatasas Alcalinas": 22222222,
            "PCR": 22222222,
            "Lactato": 22222222,
            "Albumina": 22222222,
            "Proteinas Totales": 22222222,
            "Glucosa": 22222222,
            "Trigliceridos": 22222222,
            "CK Total": 22222222,
            "CK-MB": 22222222,
            "TroponinaI": 22222222,
            "proBNP": 22222222,
            "Hb": 22222222,
            "VCM": 22222222,
            "HCM": 22222222,
            "CHCM": 22222222,
            "Plaquetas": 22222222,
            "Leucocitos": 22222222,
            "Segmentados": 22222222,
            "Eosinofilos": 22222222,
            "Linfocitos": 22222222,
            "Monocitos": 22222222,
            "Basofilos": 22222222,
            "VHS": 22222222,
            "INR": 22222222,
            "TP": 22222222,
            "TTPK": 22222222,
            "pH": 22222222,
            "pO2": 22222222,
            "pCO2": 22222222,
            "HCO3": 22222222,
            "BE": 22222222,
            "sO2": 22222222},
        {"Fecha": 1234,
            "Creatinina": 4321,
            "BUN": 777,
            "Ca": 1234,
            "Calcio Total": 1234,
            "Fosforo": 1234,
            "LDH": 1234,
            "Magnesio": 1234,
            "Na+": 1234,
            "K+": 1234,
            "Cl-": 1234,
            "Bilirrubina Total": 1234,
            "Bilirrubina Directa": 1234,
            "ASAT": 1234,
            "ALAT": 1234,
            "GamaGT": 1234,
            "Fosfatasas Alcalinas": 1234,
            "PCR": 1234,
            "Lactato": 1234,
            "Albumina": 1234,
            "Proteinas Totales": 1234,
            "Glucosa": 1234,
            "Trigliceridos": 1234,
            "CK Total": 1234,
            "CK-MB": 1234,
            "TroponinaI": 1234,
            "proBNP": 1234,
            "Hb": 1234,
            "VCM": 1234,
            "HCM": 1234,
            "CHCM": 1234,
            "Plaquetas": 1234,
            "Leucocitos": 1234,
            "Segmentados": 1234,
            "Eosinofilos": 1234,
            "Linfocitos": 1234,
            "Monocitos": 1234,
            "Basofilos": 1234,
            "VHS": 1234,
            "INR": 1234,
            "TP": 1234,
            "TTPK": 1234,
            "pH": 1234,
            "pO2": 1234,
            "pCO2": 1234,
            "HCO3": 1234,
            "BE": 1234,
            "sO2": 1234},
        {"Fecha": 22222222,
            "Creatinina": 22222222,
            "BUN": 22222222,
            "Ca": 22222222,
            "Calcio Total": 22222222,
            "Fosforo": 22222222,
            "LDH": 22222222,
            "Magnesio": 22222222,
            "Na+": 22222222,
            "K+": 22222222,
            "Cl-": 22222222,
            "Bilirrubina Total": 22222222,
            "Bilirrubina Directa": 22222222,
            "ASAT": 22222222,
            "ALAT": 22222222,
            "GamaGT": 22222222,
            "Fosfatasas Alcalinas": 22222222,
            "PCR": 22222222,
            "Lactato": 22222222,
            "Albumina": 22222222,
            "Proteinas Totales": 22222222,
            "Glucosa": 22222222,
            "Trigliceridos": 22222222,
            "CK Total": 22222222,
            "CK-MB": 22222222,
            "TroponinaI": 22222222,
            "proBNP": 22222222,
            "Hb": 22222222,
            "VCM": 22222222,
            "HCM": 22222222,
            "CHCM": 22222222,
            "Plaquetas": 22222222,
            "Leucocitos": 22222222,
            "Segmentados": 22222222,
            "Eosinofilos": 22222222,
            "Linfocitos": 22222222,
            "Monocitos": 22222222,
            "Basofilos": 22222222,
            "VHS": 22222222,
            "INR": 22222222,
            "TP": 22222222,
            "TTPK": 22222222,
            "pH": 22222222,
            "pO2": 22222222,
            "pCO2": 22222222,
            "HCO3": 22222222,
            "BE": 22222222,
            "sO2": 22222222},
        {"Fecha": 1234,
            "Creatinina": 4321,
            "BUN": 777,
            "Ca": 1234,
            "Calcio Total": 1234,
            "Fosforo": 1234,
            "LDH": 1234,
            "Magnesio": 1234,
            "Na+": 1234,
            "K+": 1234,
            "Cl-": 1234,
            "Bilirrubina Total": 1234,
            "Bilirrubina Directa": 1234,
            "ASAT": 1234,
            "ALAT": 1234,
            "GamaGT": 1234,
            "Fosfatasas Alcalinas": 1234,
            "PCR": 1234,
            "Lactato": 1234,
            "Albumina": 1234,
            "Proteinas Totales": 1234,
            "Glucosa": 1234,
            "Trigliceridos": 1234,
            "CK Total": 1234,
            "CK-MB": 1234,
            "TroponinaI": 1234,
            "proBNP": 1234,
            "Hb": 1234,
            "VCM": 1234,
            "HCM": 1234,
            "CHCM": 1234,
            "Plaquetas": 1234,
            "Leucocitos": 1234,
            "Segmentados": 1234,
            "Eosinofilos": 1234,
            "Linfocitos": 1234,
            "Monocitos": 1234,
            "Basofilos": 1234,
            "VHS": 1234,
            "INR": 1234,
            "TP": 1234,
            "TTPK": 1234,
            "pH": 1234,
            "pO2": 1234,
            "pCO2": 1234,
            "HCO3": 1234,
            "BE": 1234,
            "sO2": 1234},
        {"Fecha": 22222222,
            "Creatinina": 22222222,
            "BUN": 22222222,
            "Ca": 22222222,
            "Calcio Total": 22222222,
            "Fosforo": 22222222,
            "LDH": 22222222,
            "Magnesio": 22222222,
            "Na+": 22222222,
            "K+": 22222222,
            "Cl-": 22222222,
            "Bilirrubina Total": 22222222,
            "Bilirrubina Directa": 22222222,
            "ASAT": 22222222,
            "ALAT": 22222222,
            "GamaGT": 22222222,
            "Fosfatasas Alcalinas": 22222222,
            "PCR": 22222222,
            "Lactato": 22222222,
            "Albumina": 22222222,
            "Proteinas Totales": 22222222,
            "Glucosa": 22222222,
            "Trigliceridos": 22222222,
            "CK Total": 22222222,
            "CK-MB": 22222222,
            "TroponinaI": 22222222,
            "proBNP": 22222222,
            "Hb": 22222222,
            "VCM": 22222222,
            "HCM": 22222222,
            "CHCM": 22222222,
            "Plaquetas": 22222222,
            "Leucocitos": 22222222,
            "Segmentados": 22222222,
            "Eosinofilos": 22222222,
            "Linfocitos": 22222222,
            "Monocitos": 22222222,
            "Basofilos": 22222222,
            "VHS": 22222222,
            "INR": 22222222,
            "TP": 22222222,
            "TTPK": 22222222,
            "pH": 22222222,
            "pO2": 22222222,
            "pCO2": 22222222,
            "HCO3": 22222222,
            "BE": 22222222,
            "sO2": 22222222},
        {"Fecha": 1234,
            "Creatinina": 4321,
            "BUN": 777,
            "Ca": 1234,
            "Calcio Total": 1234,
            "Fosforo": 1234,
            "LDH": 1234,
            "Magnesio": 1234,
            "Na+": 1234,
            "K+": 1234,
            "Cl-": 1234,
            "Bilirrubina Total": 1234,
            "Bilirrubina Directa": 1234,
            "ASAT": 1234,
            "ALAT": 1234,
            "GamaGT": 1234,
            "Fosfatasas Alcalinas": 1234,
            "PCR": 1234,
            "Lactato": 1234,
            "Albumina": 1234,
            "Proteinas Totales": 1234,
            "Glucosa": 1234,
            "Trigliceridos": 1234,
            "CK Total": 1234,
            "CK-MB": 1234,
            "TroponinaI": 1234,
            "proBNP": 1234,
            "Hb": 1234,
            "VCM": 1234,
            "HCM": 1234,
            "CHCM": 1234,
            "Plaquetas": 1234,
            "Leucocitos": 1234,
            "Segmentados": 1234,
            "Eosinofilos": 1234,
            "Linfocitos": 1234,
            "Monocitos": 1234,
            "Basofilos": 1234,
            "VHS": 1234,
            "INR": 1234,
            "TP": 1234,
            "TTPK": 1234,
            "pH": 1234,
            "pO2": 1234,
            "pCO2": 1234,
            "HCO3": 1234,
            "BE": 1234,
            "sO2": 1234},
        {"Fecha": 22222222,
            "Creatinina": 22222222,
            "BUN": 22222222,
            "Ca": 22222222,
            "Calcio Total": 22222222,
            "Fosforo": 22222222,
            "LDH": 22222222,
            "Magnesio": 22222222,
            "Na+": 22222222,
            "K+": 22222222,
            "Cl-": 22222222,
            "Bilirrubina Total": 22222222,
            "Bilirrubina Directa": 22222222,
            "ASAT": 22222222,
            "ALAT": 22222222,
            "GamaGT": 22222222,
            "Fosfatasas Alcalinas": 22222222,
            "PCR": 22222222,
            "Lactato": 22222222,
            "Albumina": 22222222,
            "Proteinas Totales": 22222222,
            "Glucosa": 22222222,
            "Trigliceridos": 22222222,
            "CK Total": 22222222,
            "CK-MB": 22222222,
            "TroponinaI": 22222222,
            "proBNP": 22222222,
            "Hb": 22222222,
            "VCM": 22222222,
            "HCM": 22222222,
            "CHCM": 22222222,
            "Plaquetas": 22222222,
            "Leucocitos": 22222222,
            "Segmentados": 22222222,
            "Eosinofilos": 22222222,
            "Linfocitos": 22222222,
            "Monocitos": 22222222,
            "Basofilos": 22222222,
            "VHS": 22222222,
            "INR": 22222222,
            "TP": 22222222,
            "TTPK": 22222222,
            "pH": 22222222,
            "pO2": 22222222,
            "pCO2": 22222222,
            "HCO3": 22222222,
            "BE": 22222222,
            "sO2": 22222222},
        {"Fecha": 1234,
            "Creatinina": 4321,
            "BUN": 777,
            "Ca": 1234,
            "Calcio Total": 1234,
            "Fosforo": 1234,
            "LDH": 1234,
            "Magnesio": 1234,
            "Na+": 1234,
            "K+": 1234,
            "Cl-": 1234,
            "Bilirrubina Total": 1234,
            "Bilirrubina Directa": 1234,
            "ASAT": 1234,
            "ALAT": 1234,
            "GamaGT": 1234,
            "Fosfatasas Alcalinas": 1234,
            "PCR": 1234,
            "Lactato": 1234,
            "Albumina": 1234,
            "Proteinas Totales": 1234,
            "Glucosa": 1234,
            "Trigliceridos": 1234,
            "CK Total": 1234,
            "CK-MB": 1234,
            "TroponinaI": 1234,
            "proBNP": 1234,
            "Hb": 1234,
            "VCM": 1234,
            "HCM": 1234,
            "CHCM": 1234,
            "Plaquetas": 1234,
            "Leucocitos": 1234,
            "Segmentados": 1234,
            "Eosinofilos": 1234,
            "Linfocitos": 1234,
            "Monocitos": 1234,
            "Basofilos": 1234,
            "VHS": 1234,
            "INR": 1234,
            "TP": 1234,
            "TTPK": 1234,
            "pH": 1234,
            "pO2": 1234,
            "pCO2": 1234,
            "HCO3": 1234,
            "BE": 1234,
            "sO2": 1234},
        {"Fecha": 22222222,
            "Creatinina": 22222222,
            "BUN": 22222222,
            "Ca": 22222222,
            "Calcio Total": 22222222,
            "Fosforo": 22222222,
            "LDH": 22222222,
            "Magnesio": 22222222,
            "Na+": 22222222,
            "K+": 22222222,
            "Cl-": 22222222,
            "Bilirrubina Total": 22222222,
            "Bilirrubina Directa": 22222222,
            "ASAT": 22222222,
            "ALAT": 22222222,
            "GamaGT": 22222222,
            "Fosfatasas Alcalinas": 22222222,
            "PCR": 22222222,
            "Lactato": 22222222,
            "Albumina": 22222222,
            "Proteinas Totales": 22222222,
            "Glucosa": 22222222,
            "Trigliceridos": 22222222,
            "CK Total": 22222222,
            "CK-MB": 22222222,
            "TroponinaI": 22222222,
            "proBNP": 22222222,
            "Hb": 22222222,
            "VCM": 22222222,
            "HCM": 22222222,
            "CHCM": 22222222,
            "Plaquetas": 22222222,
            "Leucocitos": 22222222,
            "Segmentados": 22222222,
            "Eosinofilos": 22222222,
            "Linfocitos": 22222222,
            "Monocitos": 22222222,
            "Basofilos": 22222222,
            "VHS": 22222222,
            "INR": 22222222,
            "TP": 22222222,
            "TTPK": 22222222,
            "pH": 22222222,
            "pO2": 22222222,
            "pCO2": 22222222,
            "HCO3": 22222222,
            "BE": 22222222,
            "sO2": 22222222}
    ]
}